sym_api_client_python/__init__.py
sym_api_client_python/datafeed_event_service.py
sym_api_client_python/loaders.py
sym_api_client_python/auth/__init__.py
sym_api_client_python/auth/auth.py
sym_api_client_python/auth/auth_endpoint_constants.py
sym_api_client_python/auth/rsa_auth.py
sym_api_client_python/clients/__init__.py
sym_api_client_python/clients/admin_client.py
sym_api_client_python/clients/api_client.py
sym_api_client_python/clients/connections_client.py
sym_api_client_python/clients/datafeed_client.py
sym_api_client_python/clients/datafeed_client_v1.py
sym_api_client_python/clients/datafeed_client_v2.py
sym_api_client_python/clients/form_builder.py
sym_api_client_python/clients/health_check_client.py
sym_api_client_python/clients/message_client.py
sym_api_client_python/clients/presence_client.py
sym_api_client_python/clients/signals_client.py
sym_api_client_python/clients/stream_client.py
sym_api_client_python/clients/sym_bot_client.py
sym_api_client_python/clients/user_client.py
sym_api_client_python/clients/constants/DatafeedVersion.py
sym_api_client_python/clients/constants/__init__.py
sym_api_client_python/configure/__init__.py
sym_api_client_python/configure/configure.py
sym_api_client_python/exceptions/APIClientErrorException.py
sym_api_client_python/exceptions/DatafeedExpiredException.py
sym_api_client_python/exceptions/ForbiddenException.py
sym_api_client_python/exceptions/MaxRetryException.py
sym_api_client_python/exceptions/ServerErrorException.py
sym_api_client_python/exceptions/SymException.py
sym_api_client_python/exceptions/UnauthorizedException.py
sym_api_client_python/exceptions/__init__.py
sym_api_client_python/listeners/__init__.py
sym_api_client_python/listeners/connection_listener.py
sym_api_client_python/listeners/connection_listener_test_imp.py
sym_api_client_python/listeners/elements_listener.py
sym_api_client_python/listeners/elements_listener_test_imp.py
sym_api_client_python/listeners/im_listener.py
sym_api_client_python-1.3.7.dist-info/LICENSE
sym_api_client_python-1.3.7.dist-info/METADATA
sym_api_client_python-1.3.7.dist-info/WHEEL
sym_api_client_python-1.3.7.dist-info/top_level.txt
sym_api_client_python-1.3.7.dist-info/RECORD
