Metadata-Version: 2.1
Name: sym-api-client-python
Version: 1.3.7
Summary: Symphony REST API - Python Client
Home-page: https://github.com/SymphonyPlatformSolutions/symphony-api-client-python
Author: Symphony Platform Solutions
Author-email: platformsolutions@symphony.com
License: UNKNOWN
Platform: UNKNOWN
Classifier: Programming Language :: Python :: 3.6
Classifier: License :: OSI Approved :: MIT License
Classifier: Operating System :: OS Independent
License-File: LICENSE
Requires-Dist: aiohttp
Requires-Dist: aioresponses (~=0.7.2)
Requires-Dist: pyOpenSSL
Requires-Dist: rsa
Requires-Dist: requests
Requires-Dist: python-jose (~=3.2.0)
Requires-Dist: python-json-logger (~=0.1.11)
Requires-Dist: beautifulsoup4 (~=4.8.0)
Requires-Dist: Jinja2 (~=2.11.3)
Requires-Dist: requests-pkcs12 (~=1.9)
Requires-Dist: requests-toolbelt (~=0.9.1)
Requires-Dist: requests-mock (~=1.7.0)
Requires-Dist: yattag (~=1.12.2)
Requires-Dist: defusedxml (~=0.7.1)
Requires-Dist: urllib3 (~=1.26.5)
Requires-Dist: py (~=1.10.0)
